LICENSE
MANIFEST.in
README.md
quicktest.py
settings_test.py
setup.py
django_vkontakte_video.egg-info/PKG-INFO
django_vkontakte_video.egg-info/SOURCES.txt
django_vkontakte_video.egg-info/dependency_links.txt
django_vkontakte_video.egg-info/not-zip-safe
django_vkontakte_video.egg-info/requires.txt
django_vkontakte_video.egg-info/top_level.txt
vkontakte_video/__init__.py
vkontakte_video/__init__.pyc
vkontakte_video/admin.py
vkontakte_video/admin.pyc
vkontakte_video/factories.py
vkontakte_video/factories.pyc
vkontakte_video/models.py
vkontakte_video/models.pyc
vkontakte_video/tests.py
vkontakte_video/tests.pyc
vkontakte_video/migrations/0001_initial.py
vkontakte_video/migrations/0001_initial.pyc
vkontakte_video/migrations/0002_auto__del_field_video_link__chg_field_album_title.py
vkontakte_video/migrations/0002_auto__del_field_video_link__chg_field_album_title.pyc
vkontakte_video/migrations/0003_auto__add_field_video_actions_count.py
vkontakte_video/migrations/0003_auto__add_field_video_actions_count.pyc
vkontakte_video/migrations/__init__.py
vkontakte_video/migrations/__init__.pyc
vkontakte_video/sql/video.postgresql_psycopg2.sql